topsis/__init__.py
topsis/__main__.py
topsis_ashna_102117144-1.0.2.dist-info/METADATA
topsis_ashna_102117144-1.0.2.dist-info/WHEEL
topsis_ashna_102117144-1.0.2.dist-info/entry_points.txt
topsis_ashna_102117144-1.0.2.dist-info/top_level.txt
topsis_ashna_102117144-1.0.2.dist-info/RECORD
